{"cameraMode":{"drawMode":0,"name":"Shaded","section":"Shading Mode"},"sceneLighting":true,"audioPlay":false,"sceneViewState":{"m_AlwaysRefresh":false,"showFog":true,"showSkybox":true,"showFlares":true,"showImageEffects":true,"showParticleSystems":true,"showVisualEffectGraphs":true,"m_FxEnabled":true},"in2DMode":false,"pivot":{"x":223.34669494628907,"y":-65.53514099121094,"z":99.28731536865235},"rotation":{"x":0.08176234364509583,"y":0.6555253863334656,"z":-0.07161258906126023,"w":0.7473787665367127},"size":127.5408935546875,"orthographic":false}